RiskBERT/__init__.py
RiskBERT/loss_functions.py
RiskBERT/models.py
RiskBERT/utils.py
RiskBERT/simulation/data_functions.py
RiskBERT/simulation/simulation.py
RiskBERT/simulation/stock_market_example.py
RiskBERT-0.0.9.dist-info/LICENSE
RiskBERT-0.0.9.dist-info/METADATA
RiskBERT-0.0.9.dist-info/WHEEL
RiskBERT-0.0.9.dist-info/top_level.txt
RiskBERT-0.0.9.dist-info/RECORD
