Metadata-Version: 2.1
Name: RiskBERT
Version: 0.0.9
Summary: Generalized semantic regression with a BERT base.
Author-email: Heiko Wagner <heikowagner@t-online.de>
License: BSD-3-Clause
Keywords: LLM,BERT,GLM
Requires-Python: >=3.7
License-File: LICENSE
Requires-Dist: pandas
Requires-Dist: numpy
Requires-Dist: sentence-transformers
Requires-Dist: datasets
Requires-Dist: statsmodels
Requires-Dist: matplotlib
Requires-Dist: torch
Requires-Dist: accelerate
Requires-Dist: torchview
Requires-Dist: graphviz
Requires-Dist: torchvision
